log_inspector_mcp-0.4.4.dist-info/licenses/LICENSE
log_mcp/__init__.py
log_mcp/server.py
log_inspector_mcp-0.4.4.dist-info/METADATA
log_inspector_mcp-0.4.4.dist-info/WHEEL
log_inspector_mcp-0.4.4.dist-info/entry_points.txt
log_inspector_mcp-0.4.4.dist-info/top_level.txt
log_inspector_mcp-0.4.4.dist-info/RECORD
