Metadata-Version: 2.4
Name: log-inspector-mcp
Version: 0.4.4
Summary: MCP server for inspecting log files in XDG_RUNTIME_DIR/log
Author-email: Thomas Hartwig <thomas.hartwig@gmail.com>
License-Expression: MIT
Project-URL: Homepage, https://github.com/thhart/log-mcp
Requires-Python: >=3.10
License-File: LICENSE
Requires-Dist: mcp>=1.0.0
Dynamic: license-file
